fractal_network/NetworkGenerator.py
fractal_network/__init__.py
fractal_network_generator-0.0.1.dist-info/LICENSE
fractal_network_generator-0.0.1.dist-info/METADATA
fractal_network_generator-0.0.1.dist-info/WHEEL
fractal_network_generator-0.0.1.dist-info/top_level.txt
fractal_network_generator-0.0.1.dist-info/RECORD
