Metadata-Version: 2.1
Name: fractal-network-generator
Version: 0.0.1
Summary: Creating fractal networks from Monsivais et al, Chaos 30, 123146 (2020)
Home-page: https://doi.org/10.1063/5.0010638
Author: Daniel Monsivias, Chandreyee Roy
Author-email: chandreyee.roy@aalto.fi
License: UNKNOWN
Platform: UNKNOWN
Classifier: Programming Language :: Python :: 3
Classifier: License :: OSI Approved :: MIT License
Classifier: Operating System :: OS Independent
Requires-Python: >=3.6
